<?xml version="1.0" encoding="UTF-8"?>
<!--
 /**
 * Social Order
 *
 * This extension adds the feature to share an order with other people and also create the "donation" product type.
 *
 * @package ImaginationMedia\SocialOrder
 * @author Igor Ludgero Miura <igor@imaginationmedia.com>
 * @copyright Copyright (c) 2018 Imagination Media (https://www.imaginationmedia.com/)
 * @license https://opensource.org/licenses/OSL-3.0.php Open Software License 3.0
 */
 -->
<listing xmlns:xsi="http://www.w3.org/2001/XMLSchema-instance" xsi:noNamespaceSchemaLocation="urn:magento:module:Magento_Ui:etc/ui_configuration.xsd">
    <argument name="data" xsi:type="array">
        <item name="js_config" xsi:type="array">
            <item name="provider" xsi:type="string">donation_orders_listing.donation_orders_listing_data_source</item>
            <item name="deps" xsi:type="string">donation_orders_listing.donation_orders_listing_data_source</item>
        </item>
        <item name="spinner" xsi:type="string">donation_orders_columns</item>
    </argument>
    <dataSource name="donation_orders_listing_data_source">
        <argument name="dataProvider" xsi:type="configurableObject">
            <argument name="class" xsi:type="string">ImaginationMedia\SocialOrder\Ui\DataProvider\Sales\Order\Donation\DataProvider</argument>
            <argument name="name" xsi:type="string">donation_orders_listing_data_source</argument>
            <argument name="primaryFieldName" xsi:type="string">id</argument>
            <argument name="requestFieldName" xsi:type="string">id</argument>
            <argument name="data" xsi:type="array">
                <item name="config" xsi:type="array">
                    <item name="component" xsi:type="string">Magento_Ui/js/grid/provider</item>
                    <item name="update_url" xsi:type="url" path="mui/index/render"/>
                    <item name="storageConfig" xsi:type="array">
                        <item name="cacheRequests" xsi:type="boolean">false</item>
                    </item>
                </item>
            </argument>
        </argument>
    </dataSource>
    <listingToolbar name="listing_top">
        <filters name="listing_filters">
            <argument name="data" xsi:type="array">
                <item name="config" xsi:type="array">
                    <item name="statefull" xsi:type="array">
                        <item name="applied" xsi:type="boolean">false</item>
                    </item>
                    <item name="params" xsi:type="array">
                        <item name="filters_modifier" xsi:type="array"/>
                    </item>
                </item>
            </argument>
        </filters>
        <paging name="listing_paging"/>
    </listingToolbar>
    <columns name="donation_orders_columns" class="Magento\Ui\Component\Listing\Columns">
        <argument name="data" xsi:type="array">
            <item name="config" xsi:type="array">
                <item name="childDefaults" xsi:type="array">
                    <item name="fieldAction" xsi:type="array">
                        <item name="provider" xsi:type="string">salesOrders</item>
                        <item name="target" xsi:type="string">selectData</item>
                        <item name="params" xsi:type="array">
                            <item name="0" xsi:type="string">${ $.$data.rowIndex }</item>
                        </item>
                    </item>
                </item>
            </item>
        </argument>
        <actionsColumn name="actions" class="ImaginationMedia\SocialOrder\Ui\Component\Listing\Columns\Order\View">
            <argument name="data" xsi:type="array">
                <item name="config" xsi:type="array">
                    <item name="indexField" xsi:type="string">entity_id</item>
                    <item name="label" xsi:type="string" translate="true">Order</item>
                    <item name="sortOrder" xsi:type="number">0</item>
                </item>
            </argument>
        </actionsColumn>
        <column name="customer_firstname">
            <argument name="data" xsi:type="array">
                <item name="config" xsi:type="array">
                    <item name="filter" xsi:type="string">text</item>
                    <item name="label" xsi:type="string" translate="true">Customer Name</item>
                    <item name="sortOrder" xsi:type="number">10</item>
                </item>
            </argument>
        </column>
        <column name="customer_lastname">
            <argument name="data" xsi:type="array">
                <item name="config" xsi:type="array">
                    <item name="filter" xsi:type="string">text</item>
                    <item name="label" xsi:type="string" translate="true">Customer Last Name</item>
                    <item name="sortOrder" xsi:type="number">20</item>
                </item>
            </argument>
        </column>
        <column name="customer_email">
            <argument name="data" xsi:type="array">
                <item name="config" xsi:type="array">
                    <item name="filter" xsi:type="string">text</item>
                    <item name="label" xsi:type="string" translate="true">Customer E-mail</item>
                    <item name="sortOrder" xsi:type="number">30</item>
                </item>
            </argument>
        </column>
        <column name="created_at" class="Magento\Ui\Component\Listing\Columns\Date">
            <argument name="data" xsi:type="array">
                <item name="config" xsi:type="array">
                    <item name="filter" xsi:type="string">dateRange</item>
                    <item name="component" xsi:type="string">Magento_Ui/js/grid/columns/date</item>
                    <item name="dataType" xsi:type="string">date</item>
                    <item name="label" xsi:type="string" translate="true">Created At</item>
                    <item name="sortOrder" xsi:type="number">40</item>
                </item>
            </argument>
        </column>
        <column name="price" class="Magento\Catalog\Ui\Component\Listing\Columns\Price">
            <argument name="data" xsi:type="array">
                <item name="config" xsi:type="array">
                    <item name="filter" xsi:type="string">textRange</item>
                    <item name="label" xsi:type="string" translate="true">Price</item>
                    <item name="sortOrder" xsi:type="number">50</item>
                </item>
            </argument>
        </column>
        <column name="qty_invoiced" class="ImaginationMedia\SocialOrder\Ui\Component\Listing\Columns\Qty">
            <argument name="data" xsi:type="array">
                <item name="config" xsi:type="array">
                    <item name="filter" xsi:type="string">textRange</item>
                    <item name="label" xsi:type="string" translate="true">Invoiced Qty</item>
                    <item name="sortOrder" xsi:type="number">60</item>
                </item>
            </argument>
        </column>
    </columns>
</listing>